odoo/addons/base_model_restrict_update/README.rst
odoo/addons/base_model_restrict_update/__init__.py
odoo/addons/base_model_restrict_update/__manifest__.py
odoo/addons/base_model_restrict_update/i18n/base_model_restrict_update.po
odoo/addons/base_model_restrict_update/i18n/base_model_restrict_update.pot
odoo/addons/base_model_restrict_update/i18n/ja.po
odoo/addons/base_model_restrict_update/i18n/ja_JP.po
odoo/addons/base_model_restrict_update/models/__init__.py
odoo/addons/base_model_restrict_update/models/ir_model.py
odoo/addons/base_model_restrict_update/models/ir_model_access.py
odoo/addons/base_model_restrict_update/models/res_users.py
odoo/addons/base_model_restrict_update/readme/CONFIGURE.rst
odoo/addons/base_model_restrict_update/readme/CREDITS.rst
odoo/addons/base_model_restrict_update/readme/DESCRIPTION.rst
odoo/addons/base_model_restrict_update/static/description/icon.png
odoo/addons/base_model_restrict_update/static/description/index.html
odoo/addons/base_model_restrict_update/tests/__init__.py
odoo/addons/base_model_restrict_update/tests/test_base_model_restrict_update.py
odoo/addons/base_model_restrict_update/views/ir_model_views.xml
odoo/addons/base_model_restrict_update/views/res_users_views.xml
odoo12_addon_base_model_restrict_update-12.0.1.1.1.dist-info/METADATA
odoo12_addon_base_model_restrict_update-12.0.1.1.1.dist-info/WHEEL
odoo12_addon_base_model_restrict_update-12.0.1.1.1.dist-info/top_level.txt
odoo12_addon_base_model_restrict_update-12.0.1.1.1.dist-info/RECORD
